pytest_spawner/string_buffer.py
pytest_spawner/state.py
pytest_spawner/events.py
pytest_spawner/error.py
pytest_spawner/future.py
pytest_spawner/plugin.py
pytest_spawner/__init__.py
pytest_spawner/manager.py
pytest_spawner/process.py
pytest_spawner/util.py
pytest_spawner-0.1.0.dist-info/metadata.json
pytest_spawner-0.1.0.dist-info/METADATA
pytest_spawner-0.1.0.dist-info/top_level.txt
pytest_spawner-0.1.0.dist-info/DESCRIPTION.rst
pytest_spawner-0.1.0.dist-info/pbr.json
pytest_spawner-0.1.0.dist-info/entry_points.txt
pytest_spawner-0.1.0.dist-info/RECORD
pytest_spawner-0.1.0.dist-info/WHEEL
